{"ChDavis":{"player_code_id":{"code":"ChDavis","id":"Davis, Christian"},"number":"5","pos":"G","height":"6-7","height_in":79,"year_class":"So","gp":23},"CoHickman":{"player_code_id":{"code":"CoHickman","id":"Hickman, Connor"},"number":"10","pos":"G","height":"6-3","height_in":75,"year_class":"So","gp":34},"CoLinke":{"player_code_id":{"code":"CoLinke","id":"Linke, Connor"},"number":"34","pos":"F","height":"6-9","height_in":81,"year_class":"Jr","gp":17},"MaEkono":{"player_code_id":{"code":"MaEkono","id":"Ekono, Max"},"number":"2","pos":"G","height":"6-7","height_in":79,"year_class":"So","gp":0},"ZeMontgomery":{"player_code_id":{"code":"ZeMontgomery","id":"Montgomery, Zek"},"number":"3","pos":"G","height":"6-6","height_in":78,"year_class":"So","gp":29},"AhJonovic":{"player_code_id":{"code":"AhJonovic","id":"Jonovic, Ahmet"},"number":"4","pos":"F","height":"7-1","height_in":85,"year_class":"Fr","gp":5},"DaHannah":{"player_code_id":{"code":"DaHannah","id":"Hannah, Darius"},"number":"35","pos":"F","height":"6-9","height_in":81,"year_class":"Jr","gp":35},"RiMast":{"player_code_id":{"code":"RiMast","id":"Mast, Rienk"},"number":"51","pos":"F","height":"6-9","height_in":81,"year_class":"Jr","gp":29},"GoBiliew":{"player_code_id":{"code":"GoBiliew","id":"Biliew, Goanar"},"number":"25","pos":"F","height":"6-8","height_in":80,"year_class":"Jr","gp":12},"CaHardtke":{"player_code_id":{"code":"CaHardtke","id":"Hardtke, Cade"},"number":"12","pos":"G","height":"6-2","height_in":74,"year_class":"So","gp":9},"Ja\"pWeathers":{"player_code_id":{"code":"Ja\"pWeathers","id":"Weathers, James \"Pop\""},"number":"1","pos":"G","height":"6-0","height_in":72,"year_class":"Jr","gp":25},"SaHennessy":{"player_code_id":{"code":"SaHennessy","id":"Hennessy, Sam"},"number":"13","pos":"G","height":"6-2","height_in":74,"year_class":"So","gp":6},"ViTahvanaine":{"player_code_id":{"code":"ViTahvanaine","id":"Tahvanainen, Ville"},"number":"23","pos":"G","height":"6-4","height_in":76,"year_class":"Sr","gp":34},"SuAgiste":{"player_code_id":{"code":"SuAgiste","id":"Agiste, Sulaiman"},"number":"32","pos":"F","height":"6-9","height_in":81,"year_class":"Fr","gp":1},"JaHenry":{"player_code_id":{"code":"JaHenry","id":"Henry, Ja'Shon"},"number":"22","pos":"F","height":"6-6","height_in":78,"year_class":"Sr","gp":29},"MaLeons":{"player_code_id":{"code":"MaLeons","id":"Leons, Malevy"},"number":"14","pos":"F","height":"6-9","height_in":81,"year_class":"Sr","gp":35},"DuDeen":{"player_code_id":{"code":"DuDeen","id":"Deen, Duke"},"number":"21","pos":"G","height":"5-8","height_in":68,"year_class":"Jr","gp":35}}
