{"MaRandolph":{"player_code_id":{"code":"MaRandolph","id":"Randolph, Marcus"},"number":"2","pos":"G","height":"6-5","height_in":77,"year_class":"So","gp":33},"MaDread":{"player_code_id":{"code":"MaDread","id":"Dread, Malcolm"},"number":"12","pos":"G","height":"6-4","height_in":76,"year_class":"Fr","gp":3},"TyBurton":{"player_code_id":{"code":"TyBurton","id":"Burton, Tyler"},"number":"3","pos":"F","height":"6-7","height_in":79,"year_class":"Sr","gp":33},"MaGrace":{"player_code_id":{"code":"MaGrace","id":"Grace, Matt"},"number":"15","pos":"F","height":"6-9","height_in":81,"year_class":"Sr","gp":29},"GaArizin":{"player_code_id":{"code":"GaArizin","id":"Arizin, Gabe"},"number":"34","pos":"G","height":"6-4","height_in":76,"year_class":"Sr","gp":4},"JaNelson":{"player_code_id":{"code":"JaNelson","id":"Nelson, Jason"},"number":"1","pos":"G","height":"5-10","height_in":70,"year_class":"Fr","gp":32},"CoCrabtree":{"player_code_id":{"code":"CoCrabtree","id":"Crabtree, Connor"},"number":"5","pos":"G","height":"6-6","height_in":78,"year_class":"Sr","gp":7},"DjBailey":{"player_code_id":{"code":"DjBailey","id":"Bailey, Dji"},"number":"4","pos":"G","height":"6-5","height_in":77,"year_class":"Jr","gp":20},"IsBigelow":{"player_code_id":{"code":"IsBigelow","id":"Bigelow, Isaiah"},"number":"24","pos":"F","height":"6-7","height_in":79,"year_class":"Sr","gp":32},"LiWeaver":{"player_code_id":{"code":"LiWeaver","id":"Weaver, Liam"},"number":"10","pos":"G","height":"6-2","height_in":74,"year_class":"So","gp":2},"AnGustavson":{"player_code_id":{"code":"AnGustavson","id":"Gustavson, Andre"},"number":"22","pos":"G","height":"6-5","height_in":77,"year_class":"Sr","gp":33},"JaRoche":{"player_code_id":{"code":"JaRoche","id":"Roche, Jason"},"number":"11","pos":"G","height":"6-5","height_in":77,"year_class":"So","gp":32},"NeQuinn":{"player_code_id":{"code":"NeQuinn","id":"Quinn, Neal"},"number":"32","pos":"C","height":"7-0","height_in":84,"year_class":"Sr","gp":33},"AiNoyes":{"player_code_id":{"code":"AiNoyes","id":"Noyes, Aidan"},"number":"35","pos":"F","height":"6-7","height_in":79,"year_class":"Fr","gp":12},"QuSouthall":{"player_code_id":{"code":"QuSouthall","id":"Southall, Quentin"},"number":"25","pos":"G","height":"6-3","height_in":75,"year_class":"Jr","gp":2},"MiWalz":{"player_code_id":{"code":"MiWalz","id":"Walz, Mike"},"number":"21","pos":"C","height":"6-11","height_in":83,"year_class":"Fr","gp":13}}
