{"LuWinslow":{"player_code_id":{"code":"LuWinslow","id":"Winslow, Luke"},"number":"20","pos":"G","height":"6-2","height_in":74,"year_class":"So","gp":12},"LaJones":{"player_code_id":{"code":"LaJones","id":"Jones, Lajae"},"number":"10","pos":"G","height":"6-7","height_in":79,"year_class":"Fr","gp":10},"NaAyala":{"player_code_id":{"code":"NaAyala","id":"Ayala, Nasan"},"number":"24","pos":"G","height":"6-3","height_in":75,"year_class":"Jr","gp":0},"TyArchibald":{"player_code_id":{"code":"TyArchibald","id":"Archibald , Tydan"},"number":"44","pos":"G","height":"6-0","height_in":72,"year_class":"Jr","gp":20},"ShBogues":{"player_code_id":{"code":"ShBogues","id":"Bogues, Shamir"},"number":"3","pos":"G","height":"6-4","height_in":76,"year_class":"So","gp":34},"LuWilliams":{"player_code_id":{"code":"LuWilliams","id":"Williams, Lue"},"number":"5","pos":"G","height":"6-5","height_in":77,"year_class":"Jr","gp":34},"NoMcdavid":{"player_code_id":{"code":"NoMcdavid","id":"McDavid, Noah"},"number":"1","pos":"G","height":"6-5","height_in":77,"year_class":"So","gp":21},"RoBrown":{"player_code_id":{"code":"RoBrown","id":"Brown, Rod"},"number":"0","pos":"F","height":"6-7","height_in":79,"year_class":"Sr","gp":23},"FrHicks":{"player_code_id":{"code":"FrHicks","id":"Hicks, Freddy"},"number":"2","pos":"G","height":"6-6","height_in":78,"year_class":"So","gp":23},"CoRushin":{"player_code_id":{"code":"CoRushin","id":"Rushin, Coreyoun"},"number":"25","pos":"F","height":"6-6","height_in":78,"year_class":"Sr","gp":27},"KiGaddy":{"player_code_id":{"code":"KiGaddy","id":"Gaddy, KiAndre"},"number":"15","pos":"F","height":"6-6","height_in":78,"year_class":"Jr","gp":28},"ShDaniel":{"player_code_id":{"code":"ShDaniel","id":"Daniel, Shakur"},"number":"13","pos":"G","height":"6-6","height_in":78,"year_class":"Sr","gp":33},"JaThomas":{"player_code_id":{"code":"JaThomas","id":"Thomas, Jalen"},"number":"22","pos":"G","height":"6-0","height_in":72,"year_class":"Jr","gp":10},"JaSmith":{"player_code_id":{"code":"JaSmith","id":"Smith, Jakorie"},"number":"23","pos":"F","height":"6-6","height_in":78,"year_class":"Jr","gp":29},"JaHopkins":{"player_code_id":{"code":"JaHopkins","id":"Hopkins, Javontae"},"number":"14","pos":"G","height":"6-0","height_in":72,"year_class":"Jr","gp":31},"GaClark":{"player_code_id":{"code":"GaClark","id":"Clark, Garry"},"number":"33","pos":"F","height":"6-7","height_in":79,"year_class":"So","gp":29},"TiBooker":{"player_code_id":{"code":"TiBooker","id":"Booker, Tiger"},"number":"12","pos":"G","height":"5-10","height_in":70,"year_class":"Jr","gp":29},"TiFerguson":{"player_code_id":{"code":"TiFerguson","id":"Ferguson, Timothy"},"number":"35","pos":"G","height":"6-2","height_in":74,"year_class":"Fr","gp":0},"MaGatkuoth":{"player_code_id":{"code":"MaGatkuoth","id":"Gatkuoth, Mareng"},"number":"4","pos":"G","height":"6-6","height_in":78,"year_class":"Jr","gp":9}}
