{"SeMoore":{"player_code_id":{"code":"SeMoore","id":"Moore, Sean"},"number":"3","pos":"G","height":"6-5","height_in":77,"year_class":"Sr.","gp":0,"origin":"Reynoldsburg, OH"},"BoMontgomery":{"player_code_id":{"code":"BoMontgomery","id":"Montgomery, Bo"},"number":"0","pos":"G","height":"6-5","height_in":77,"year_class":"Sr.","gp":0,"origin":"Memphis, TN"},"JoCorbin":{"player_code_id":{"code":"JoCorbin","id":"Corbin, Josh"},"number":"32","pos":"G","height":"6-3","height_in":75,"year_class":"Sr.","gp":0,"origin":"Gahanna, OH"},"ShAnthony":{"player_code_id":{"code":"ShAnthony","id":"Anthony, Shane"},"number":"12","pos":"G","height":"6-2","height_in":74,"year_class":"So.","gp":0,"origin":"Raleigh, NC"},"NoRoss":{"player_code_id":{"code":"NoRoss","id":"Ross, Noah"},"number":"5","pos":"G","height":"6-7","height_in":79,"year_class":"Jr.","gp":0,"origin":"Apex, NC"},"GrWilliams":{"player_code_id":{"code":"GrWilliams","id":"Williams, Greedy"},"number":"7","pos":"G","height":"6-5","height_in":77,"year_class":"Jr.","gp":0,"origin":"Fort Montgomery, NY"},"HaObioha":{"player_code_id":{"code":"HaObioha","id":"Obioha, Harlan"},"number":"55","pos":"C","height":"7-0","height_in":84,"year_class":"Jr.","gp":0,"origin":"Hoxie, KS"},"NoHodge":{"player_code_id":{"code":"NoHodge","id":"Hodge, Nolan"},"number":"4","pos":"G","height":"6-7","height_in":79,"year_class":"Jr.","gp":0,"origin":"Greensboro, NC"},"JoFullwood":{"player_code_id":{"code":"JoFullwood","id":"Fullwood, JoJo"},"number":"22","pos":"G","height":"6-2","height_in":74,"year_class":"Jr.","gp":0,"origin":"Burgaw, NC"},"JaMurphy":{"player_code_id":{"code":"JaMurphy","id":"Murphy, Jake"},"number":"8","pos":"G","height":"6-4","height_in":76,"year_class":"Jr.","gp":0,"origin":"Phoenix, AZ"},"__coach__":{"player_code_id":{"code":"__coach__","id":"Takayo Siddle"},"number":"","pos":"","height":"","year_class":"","gp":-1},"MaMoore":{"player_code_id":{"code":"MaMoore","id":"Moore, Matthew"},"number":"10","pos":"F","height":"6-8","height_in":80,"year_class":"So.","gp":0,"origin":"Chicago, IL"},"KhMcgriff":{"player_code_id":{"code":"KhMcgriff","id":"McGriff, Khamari"},"number":"21","pos":"F","height":"6-8","height_in":80,"year_class":"Sr.","gp":0,"origin":"Tallahassee, FL"},"ElJamison":{"player_code_id":{"code":"ElJamison","id":"Jamison, Elijah"},"number":"2","pos":"G","height":"6-3","height_in":75,"year_class":"Jr.","gp":0,"origin":"Louisburg, NC"},"DoNewby":{"player_code_id":{"code":"DoNewby","id":"Newby, Donovan"},"number":"1","pos":"G","height":"6-1","height_in":73,"year_class":"Sr.","gp":0,"origin":"Chicago Heights, IL"},"MaMabor":{"player_code_id":{"code":"MaMabor","id":"Mabor, Makoi"},"number":"13","pos":"F","height":"6-11","height_in":83,"year_class":"Fr.","gp":0,"origin":"Rumbek, South Sudan"},"MaSmith":{"player_code_id":{"code":"MaSmith","id":"Smith, Makel"},"number":"6","pos":"G","height":"6-0","height_in":72,"year_class":"Fr.","gp":0,"origin":"Eden, NC"},"KeCave":{"player_code_id":{"code":"KeCave","id":"Cave, Kendell"},"number":"9","pos":"F","height":"6-5","height_in":77,"year_class":"So.","gp":0,"origin":"Wallace, NC"}}
