{"TaBynum":{"player_code_id":{"code":"TaBynum","id":"Bynum, Tamir"},"number":"15","pos":"G","height":"6-2","height_in":74,"year_class":"Jr","gp":0},"RaHolmes":{"player_code_id":{"code":"RaHolmes","id":"Holmes, Rashad"},"number":"32","pos":"G","height":"5-11","height_in":71,"year_class":"Fr","gp":6},"RoCarson":{"player_code_id":{"code":"RoCarson","id":"Carson, Rodney"},"number":"24","pos":"G","height":"6-3","height_in":75,"year_class":"So","gp":25},"LaRobinson":{"player_code_id":{"code":"LaRobinson","id":"Robinson III, Larry"},"number":"20","pos":"G","height":"5-11","height_in":71,"year_class":"Sr","gp":3},"LaBerzat":{"player_code_id":{"code":"LaBerzat","id":"Berzat, Lamont"},"number":"2","pos":"G","height":"5-6","height_in":66,"year_class":"Sr","gp":25},"DeStHilaire":{"player_code_id":{"code":"DeStHilaire","id":"St. Hilaire, Derek"},"number":"10","pos":"G","height":"6-0","height_in":72,"year_class":"Sr","gp":25},"NoWilliams":{"player_code_id":{"code":"NoWilliams","id":"Williams, Norris"},"number":"12","pos":"G","height":"6-2","height_in":74,"year_class":"Fr","gp":0},"AbFrye":{"player_code_id":{"code":"AbFrye","id":"Frye, Abiram"},"number":"20","pos":"G","height":"6-2","height_in":74,"year_class":"Fr","gp":1},"KmDoughty":{"player_code_id":{"code":"KmDoughty","id":"Doughty, Kmani"},"number":"13","pos":"G","height":"6-5","height_in":77,"year_class":"Fr","gp":22},"D'Bell":{"player_code_id":{"code":"D'Bell","id":"Bell, D'Ante"},"number":"33","pos":"F","height":"6-9","height_in":81,"year_class":"Fr","gp":8},"LaMarshall":{"player_code_id":{"code":"LaMarshall","id":"Marshall, Ladarius"},"number":"23","pos":"F","height":"6-6","height_in":78,"year_class":"Jr","gp":22},"ChBohannon":{"player_code_id":{"code":"ChBohannon","id":"Bohannon, Charles"},"number":"5","pos":"G","height":"6-0","height_in":72,"year_class":"Sr","gp":12},"TrGreen":{"player_code_id":{"code":"TrGreen","id":"Green, Troy"},"number":"3","pos":"G","height":"6-3","height_in":75,"year_class":"Sr","gp":25},"DaRosser":{"player_code_id":{"code":"DaRosser","id":"Rosser, Damion"},"number":"1","pos":"G","height":"6-4","height_in":76,"year_class":"Sr","gp":25},"AhFreeman":{"player_code_id":{"code":"AhFreeman","id":"Freeman, Ahren"},"number":"11","pos":"F","height":"6-6","height_in":78,"year_class":"So","gp":23},"JaMyers":{"player_code_id":{"code":"JaMyers","id":"Myers, Jahmel"},"number":"4","pos":"F","height":"6-7","height_in":79,"year_class":"Jr","gp":25},"BoTong":{"player_code_id":{"code":"BoTong","id":"Tong, Bol"},"number":"21","pos":"F","height":"6-9","height_in":81,"year_class":"Jr","gp":8},"JaRodgers":{"player_code_id":{"code":"JaRodgers","id":"Rodgers, Jay"},"number":"0","pos":"G","height":"6-3","height_in":75,"year_class":"Fr","gp":11}}
