{"KeDinwiddie":{"player_code_id":{"code":"KeDinwiddie","id":"Dinwiddie, Keith"},"number":"10","pos":"G","height":"6-2","height_in":74,"year_class":"Fr","gp":7},"NaMensah":{"player_code_id":{"code":"NaMensah","id":"Mensah, Nathan"},"number":"31","pos":"F","height":"6-10","height_in":82,"year_class":"Jr","gp":28},"TyBroughton":{"player_code_id":{"code":"TyBroughton","id":"Broughton, Tyler"},"number":"24","pos":"G","height":"6-4","height_in":76,"year_class":"Fr","gp":4},"ChEvans":{"player_code_id":{"code":"ChEvans","id":"Evans, Che"},"number":"12","pos":"F","height":"6-7","height_in":79,"year_class":"Fr","gp":10},"JoTomaic":{"player_code_id":{"code":"JoTomaic","id":"Tomaic, Joshua"},"number":"23","pos":"F","height":"6-9","height_in":81,"year_class":"Sr","gp":28},"JoSchakel":{"player_code_id":{"code":"JoSchakel","id":"Schakel, Jordan"},"number":"20","pos":"G","height":"6-6","height_in":78,"year_class":"Sr","gp":28},"DeMorhar":{"player_code_id":{"code":"DeMorhar","id":"Morhar, Derek"},"number":"32","pos":"G","height":"6-5","height_in":77,"year_class":"Fr","gp":0},"TrPulliam":{"player_code_id":{"code":"TrPulliam","id":"Pulliam, Trey"},"number":"4","pos":"G","height":"6-3","height_in":75,"year_class":"Sr","gp":28},"TeGomez":{"player_code_id":{"code":"TeGomez","id":"Gomez, Terrell"},"number":"3","pos":"G","height":"5-8","height_in":68,"year_class":"Sr","gp":28},"AgArop":{"player_code_id":{"code":"AgArop","id":"Arop, Aguek"},"number":"33","pos":"F","height":"6-6","height_in":78,"year_class":"Jr","gp":20},"JaBarnett":{"player_code_id":{"code":"JaBarnett","id":"Barnett, Jared"},"number":"21","pos":"G","height":"6-1","height_in":73,"year_class":"So","gp":8},"CaAlger":{"player_code_id":{"code":"CaAlger","id":"Alger, Cade"},"number":"14","pos":"F","height":"6-9","height_in":81,"year_class":"Fr","gp":8},"LaButler":{"player_code_id":{"code":"LaButler","id":"Butler, Lamont"},"number":"5","pos":"G","height":"6-2","height_in":74,"year_class":"Fr","gp":28},"AdSeiko":{"player_code_id":{"code":"AdSeiko","id":"Seiko, Adam"},"number":"2","pos":"G","height":"6-3","height_in":75,"year_class":"Jr","gp":27},"TrBroughton":{"player_code_id":{"code":"TrBroughton","id":"Broughton, Triston"},"number":"42","pos":"G","height":"6-4","height_in":76,"year_class":"Fr","gp":4},"MaMitchell":{"player_code_id":{"code":"MaMitchell","id":"Mitchell, Matt"},"number":"11","pos":"F","height":"6-6","height_in":78,"year_class":"Sr","gp":25},"KeJohnson":{"player_code_id":{"code":"KeJohnson","id":"Johnson, Keshad"},"number":"0","pos":"F","height":"6-7","height_in":79,"year_class":"So","gp":24}}
