{"GrHammond":{"player_code_id":{"code":"GrHammond","id":"Hammond, Gregory"},"number":"3","pos":"G","height":"6-6","height_in":78,"year_class":"So","gp":13},"ObNoel":{"player_code_id":{"code":"ObNoel","id":"Noel, Obadiah"},"number":"11","pos":"G","height":"6-4","height_in":76,"year_class":"Sr","gp":18},"AlBlunt":{"player_code_id":{"code":"AlBlunt","id":"Blunt, Allin"},"number":"15","pos":"F","height":"6-7","height_in":79,"year_class":"Jr","gp":23},"DaJordan-tho":{"player_code_id":{"code":"DaJordan-tho","id":"Jordan-Thomas, Darion"},"number":"12","pos":"F","height":"6-7","height_in":79,"year_class":"So","gp":19},"SaBoudie":{"player_code_id":{"code":"SaBoudie","id":"Boudie, Salif"},"number":"23","pos":"F","height":"6-8","height_in":80,"year_class":"Sr","gp":23},"ChRussell":{"player_code_id":{"code":"ChRussell","id":"Russell Jr., Charlie"},"number":"4","pos":"F","height":"6-8","height_in":80,"year_class":"So","gp":1},"RoMitchell":{"player_code_id":{"code":"RoMitchell","id":"Mitchell, Ron"},"number":"00","pos":"G","height":"6-3","height_in":75,"year_class":"So","gp":19},"KaThomas":{"player_code_id":{"code":"KaThomas","id":"Thomas, Kalil"},"number":"02","pos":"G","height":"6-4","height_in":76,"year_class":"So","gp":22},"CaBates":{"player_code_id":{"code":"CaBates","id":"Bates, Caleb"},"number":"22","pos":"F","height":"6-7","height_in":79,"year_class":"Fr","gp":1},"RiGreaves":{"player_code_id":{"code":"RiGreaves","id":"Greaves, Richie"},"number":"21","pos":"G","height":"6-1","height_in":73,"year_class":"Fr","gp":1},"MaBrooks":{"player_code_id":{"code":"MaBrooks","id":"Brooks, Max"},"number":"10","pos":"F","height":"6-7","height_in":79,"year_class":"Fr","gp":23},"AnBlunt":{"player_code_id":{"code":"AnBlunt","id":"Blunt, Anthony"},"number":"14","pos":"G","height":"6-2","height_in":74,"year_class":"Fr","gp":18},"CoWithers":{"player_code_id":{"code":"CoWithers","id":"Withers, Connor"},"number":"05","pos":"F","height":"6-7","height_in":79,"year_class":"So","gp":21},"BrDaley":{"player_code_id":{"code":"BrDaley","id":"Daley, Bryce"},"number":"01","pos":"G","height":"6-3","height_in":75,"year_class":"Jr","gp":23}}
