{"AlVantimmere":{"player_code_id":{"code":"AlVantimmere","id":"VanTimmeren, Ally"},"number":"12","pos":"F","height":"6-2","height_in":74,"year_class":"Fr","gp":3},"MaDickens":{"player_code_id":{"code":"MaDickens","id":"Dickens, Makayla"},"number":"10","pos":"G","height":"5-8","height_in":68,"year_class":"Sr","gp":3},"MaGakdeng":{"player_code_id":{"code":"MaGakdeng","id":"Gakdeng, Maria"},"number":"5","pos":"C","height":"6-3","height_in":75,"year_class":"Fr","gp":3},"JoLacey":{"player_code_id":{"code":"JoLacey","id":"Lacey, JoJo"},"number":"4","pos":"G","height":"6-1","height_in":73,"year_class":"So","gp":3},"JaBatts":{"player_code_id":{"code":"JaBatts","id":"Batts, Jaelyn"},"number":"3","pos":"F","height":"6-0","height_in":72,"year_class":"Jr","gp":3},"DoWaggoner":{"player_code_id":{"code":"DoWaggoner","id":"Waggoner, Dontavia"},"number":"0","pos":"G","height":"6-0","height_in":72,"year_class":"So","gp":3},"CaSwartz":{"player_code_id":{"code":"CaSwartz","id":"Swartz, Cameron"},"number":"1","pos":"G","height":"5-11","height_in":71,"year_class":"Sr","gp":3},"AnDaley":{"player_code_id":{"code":"AnDaley","id":"Daley, Andrea"},"number":"21","pos":"G","height":"6-0","height_in":72,"year_class":"Fr","gp":3},"AlPalmieri":{"player_code_id":{"code":"AlPalmieri","id":"Palmieri, Allie"},"number":"24","pos":"G","height":"5-10","height_in":70,"year_class":"Fr","gp":2},"ClFord":{"player_code_id":{"code":"ClFord","id":"Ford, Clara"},"number":"32","pos":"F","height":"6-3","height_in":75,"year_class":"Sr","gp":3},"MaGarraud":{"player_code_id":{"code":"MaGarraud","id":"Garraud, Marnelle"},"number":"14","pos":"G","height":"5-7","height_in":67,"year_class":"Sr","gp":3},"AkKonkwo":{"player_code_id":{"code":"AkKonkwo","id":"Konkwo, Akunna"},"number":"44","pos":"C","height":"6-2","height_in":74,"year_class":"Jr","gp":0},"AmFields":{"player_code_id":{"code":"AmFields","id":"Fields, Amaria"},"number":"11","pos":"G","height":"5-11","height_in":71,"year_class":"Fr","gp":0},"TaSoule":{"player_code_id":{"code":"TaSoule","id":"Soule, Taylor"},"number":"13","pos":"F","height":"5-11","height_in":71,"year_class":"Sr","gp":3},"KaIvey":{"player_code_id":{"code":"KaIvey","id":"Ivey, Kaylah"},"number":"2","pos":"G","height":"5-8","height_in":68,"year_class":"So","gp":3}}
