{"JaSimmons":{"player_code_id":{"code":"JaSimmons","id":"Simmons, Jasmine"},"number":"43","pos":"G","height":"5-11","height_in":71,"year_class":"Jr","gp":20},"JoSubasic":{"player_code_id":{"code":"JoSubasic","id":"Subasic, Jovana"},"number":"41","pos":"F","height":"6-4","height_in":76,"year_class":"Sr","gp":10},"SaGoforth":{"player_code_id":{"code":"SaGoforth","id":"Goforth, Sasha"},"number":"13","pos":"G","height":"6-1","height_in":73,"year_class":"Fr","gp":20},"TaJones":{"player_code_id":{"code":"TaJones","id":"Jones, Taylor"},"number":"44","pos":"F","height":"6-4","height_in":76,"year_class":"So","gp":20},"AnTeFaustino":{"player_code_id":{"code":"AnTeFaustino","id":"Faustino, Ana Teresa"},"number":"11","pos":"G","height":"5-7","height_in":67,"year_class":"Fr","gp":5},"TaVoOelhoffen":{"player_code_id":{"code":"TaVoOelhoffen","id":"von Oelhoffen, Talia"},"number":"22","pos":"G","height":"5-11","height_in":71,"year_class":"Fr","gp":13},"NoMannen":{"player_code_id":{"code":"NoMannen","id":"Mannen, Noelle"},"number":"4","pos":"G","height":"5-6","height_in":66,"year_class":"So","gp":8},"JeMitrovic":{"player_code_id":{"code":"JeMitrovic","id":"Mitrovic, Jelena"},"number":"12","pos":"C","height":"6-8","height_in":80,"year_class":"Fr","gp":20},"TaCorosdale":{"player_code_id":{"code":"TaCorosdale","id":"Corosdale, Taya"},"number":"5","pos":"F","height":"6-3","height_in":75,"year_class":"Jr","gp":20},"AnAquino":{"player_code_id":{"code":"AnAquino","id":"Aquino, Andrea"},"number":"2","pos":"F","height":"6-9","height_in":81,"year_class":"So","gp":0},"AlGoodman":{"player_code_id":{"code":"AlGoodman","id":"Goodman, Aleah"},"number":"01","pos":"G","height":"5-9","height_in":69,"year_class":"Sr","gp":20},"ElMack":{"player_code_id":{"code":"ElMack","id":"Mack, Ellie"},"number":"20","pos":"F","height":"6-3","height_in":75,"year_class":"Sr","gp":20},"KeBrown":{"player_code_id":{"code":"KeBrown","id":"Brown, Kennedy"},"number":"42","pos":"F","height":"6-6","height_in":78,"year_class":"So","gp":0},"SaSamuel":{"player_code_id":{"code":"SaSamuel","id":"Samuel, Savannah"},"number":"24","pos":"G","height":"6-1","height_in":73,"year_class":"Fr","gp":19}}
