{"DaGreen":{"player_code_id":{"code":"DaGreen","id":"Green, Da'Ja"},"number":"10","pos":"G","height":"5-6","height_in":66,"year_class":"Sr","gp":25},"ElKitley":{"player_code_id":{"code":"ElKitley","id":"Kitley, Elizabeth"},"number":"33","pos":"C","height":"6-5","height_in":77,"year_class":"So","gp":25},"ShCalhoun":{"player_code_id":{"code":"ShCalhoun","id":"Calhoun, Shelby"},"number":"12","pos":"G","height":"5-11","height_in":71,"year_class":"Fr","gp":4},"NeDean":{"player_code_id":{"code":"NeDean","id":"Dean, Nevaeh"},"number":"31","pos":"F","height":"6-2","height_in":74,"year_class":"Fr","gp":0},"CaKing":{"player_code_id":{"code":"CaKing","id":"King, Cayla"},"number":"22","pos":"G","height":"5-11","height_in":71,"year_class":"So","gp":25},"D'Gregg":{"player_code_id":{"code":"D'Gregg","id":"Gregg, D'asia"},"number":"11","pos":"F","height":"6-2","height_in":74,"year_class":"Jr","gp":17},"AlObouhFegue":{"player_code_id":{"code":"AlObouhFegue","id":"Obouh Fegue, Alex"},"number":"40","pos":"C","height":"6-4","height_in":76,"year_class":"Sr","gp":11},"GeAmoore":{"player_code_id":{"code":"GeAmoore","id":"Amoore, Georgia"},"number":"5","pos":"G","height":"5-5","height_in":65,"year_class":"Fr","gp":25},"AsJones":{"player_code_id":{"code":"AsJones","id":"Jones, Asiah"},"number":"23","pos":"F","height":"6-3","height_in":75,"year_class":"Sr","gp":12},"AiSheppard":{"player_code_id":{"code":"AiSheppard","id":"Sheppard, Aisha"},"number":"2","pos":"G","height":"5-9","height_in":69,"year_class":"Sr","gp":25},"ShKing":{"player_code_id":{"code":"ShKing","id":"King, Shamarla"},"number":"21","pos":"G","height":"6-0","height_in":72,"year_class":"Fr","gp":0},"AzBaines":{"player_code_id":{"code":"AzBaines","id":"Baines, Azana"},"number":"15","pos":"G","height":"6-1","height_in":73,"year_class":"So","gp":18},"MaEnnis":{"player_code_id":{"code":"MaEnnis","id":"Ennis, Makayla"},"number":"0","pos":"G","height":"6-0","height_in":72,"year_class":"So","gp":19},"TaGeiman":{"player_code_id":{"code":"TaGeiman","id":"Geiman, Taylor"},"number":"35","pos":"G","height":"6-0","height_in":72,"year_class":"So","gp":8},"ChBrooks":{"player_code_id":{"code":"ChBrooks","id":"Brooks, Chloe"},"number":"3","pos":"G","height":"5-10","height_in":70,"year_class":"So","gp":7}}
