{"IsJasey":{"player_code_id":{"code":"IsJasey","id":"Jasey, Isiah"},"number":"22","pos":"F","height":"6-10","height_in":82,"year_class":"Jr","gp":20},"TyJolly":{"player_code_id":{"code":"TyJolly","id":"Jolly, Tyson"},"number":"0","pos":"G","height":"6-4","height_in":76,"year_class":"Jr","gp":30},"ChSmith":{"player_code_id":{"code":"ChSmith","id":"Smith IV, Charles"},"number":"4","pos":"G","height":"6-5","height_in":77,"year_class":"Fr","gp":22},"JaYoung":{"player_code_id":{"code":"JaYoung","id":"Young Jr., Jahmar"},"number":"21","pos":"F","height":"6-9","height_in":81,"year_class":"So","gp":0},"EtChargois":{"player_code_id":{"code":"EtChargois","id":"Chargois, Ethan"},"number":"25","pos":"F","height":"6-9","height_in":81,"year_class":"Jr","gp":28},"DaMcneill":{"player_code_id":{"code":"DaMcneill","id":"McNeill, Darius"},"number":"2","pos":"G","height":"6-3","height_in":75,"year_class":"Jr","gp":0},"KeDavis":{"player_code_id":{"code":"KeDavis","id":"Davis, Kendric"},"number":"3","pos":"G","height":"5-11","height_in":71,"year_class":"So","gp":26},"DaMcbride":{"player_code_id":{"code":"DaMcbride","id":"McBride, Darius"},"number":"33","pos":"G","height":"6-4","height_in":76,"year_class":"Fr","gp":0},"GrYoungkin":{"player_code_id":{"code":"GrYoungkin","id":"Youngkin, Grant"},"number":"20","pos":"G","height":"6-3","height_in":75,"year_class":"Jr","gp":8},"IsMike":{"player_code_id":{"code":"IsMike","id":"Mike, Isiaha"},"number":"15","pos":"F","height":"6-8","height_in":80,"year_class":"Jr","gp":30},"CjWhite":{"player_code_id":{"code":"CjWhite","id":"White, CJ"},"number":"13","pos":"G","height":"6-5","height_in":77,"year_class":"So","gp":29},"FeHunt":{"player_code_id":{"code":"FeHunt","id":"Hunt, Feron"},"number":"1","pos":"F","height":"6-8","height_in":80,"year_class":"So","gp":30},"EmBandoumel":{"player_code_id":{"code":"EmBandoumel","id":"Bandoumel, Emmanuel"},"number":"5","pos":"G","height":"6-4","height_in":76,"year_class":"So","gp":30},"AlTabor":{"player_code_id":{"code":"AlTabor","id":"Tabor Jr., Alex"},"number":"23","pos":"G","height":"6-2","height_in":74,"year_class":"Fr","gp":7},"WiDouglas":{"player_code_id":{"code":"WiDouglas","id":"Douglas, William"},"number":"14","pos":"G","height":"6-5","height_in":77,"year_class":"Jr","gp":3},"EvRay":{"player_code_id":{"code":"EvRay","id":"Ray, Everett"},"number":"24","pos":"F","height":"6-7","height_in":79,"year_class":"So","gp":19}}
