{"EmRonsiek":{"player_code_id":{"code":"EmRonsiek","id":"Ronsiek, Emma"},"number":"31","pos":"F","height":"6-1","height_in":73,"year_class":"Sr.","gp":32,"origin":"Sioux Falls, SD"},"KiLockett":{"player_code_id":{"code":"KiLockett","id":"Lockett, Kiani"},"number":"11","pos":"G","height":"5-8","height_in":68,"year_class":"So.","gp":19,"origin":"Minneapolis, MN"},"KeTownsend":{"player_code_id":{"code":"KeTownsend","id":"Townsend, Kennedy"},"number":"2","pos":"G","height":"5-10","height_in":70,"year_class":"So.","gp":31,"origin":"Kansas City, MO"},"LaJensen":{"player_code_id":{"code":"LaJensen","id":"Jensen, Lauren"},"number":"15","pos":"G","height":"5-10","height_in":70,"year_class":"Sr.","gp":32,"origin":"Lakeville, MN"},"McMiller":{"player_code_id":{"code":"McMiller","id":"Miller, McKayla"},"number":"32","pos":"G","height":"6-1","height_in":73,"year_class":"Fr.","gp":20,"origin":"Cimarron, KS"},"MoMogensen":{"player_code_id":{"code":"MoMogensen","id":"Mogensen, Molly"},"number":"21","pos":"G","height":"5-7","height_in":67,"year_class":"Sr.","gp":32,"origin":"Farmington, MN"},"__coach__":{"player_code_id":{"code":"__coach__","id":"Jim Flanery"},"number":"","pos":"","height":"","year_class":"","gp":-1},"JaHoran":{"player_code_id":{"code":"JaHoran","id":"Horan, Jayme"},"number":"12","pos":"G","height":"5-10","height_in":70,"year_class":"Sr.","gp":30,"origin":"Omaha, NE"},"BrHarshaw":{"player_code_id":{"code":"BrHarshaw","id":"Harshaw, Brittany"},"number":"23","pos":"G","height":"6-1","height_in":73,"year_class":"Fr.","gp":27,"origin":"Andover, KS"},"MoMaly":{"player_code_id":{"code":"MoMaly","id":"Maly, Morgan"},"number":"30","pos":"G","height":"6-1","height_in":73,"year_class":"Sr.","gp":32,"origin":"Crete, NE"},"LeUnruh":{"player_code_id":{"code":"LeUnruh","id":"Unruh, Lexi"},"number":"4","pos":"G","height":"6-1","height_in":73,"year_class":"Fr.","gp":1,"origin":"Sioux Falls, SD"},"MaBrake":{"player_code_id":{"code":"MaBrake","id":"Brake, Mallory"},"number":"14","pos":"F","height":"6-0","height_in":72,"year_class":"Sr.","gp":32,"origin":"Hastings, MN"}}
