{"JaEllis":{"player_code_id":{"code":"JaEllis","id":"Ellis, Jaden"},"number":"3","pos":"G","height":"6-0","height_in":72,"year_class":"So.","gp":12,"origin":"Greensboro, NC"},"JaCross":{"player_code_id":{"code":"JaCross","id":"Cross, Jared"},"number":"24","pos":"G","height":"6-3","height_in":75,"year_class":"Sr.","gp":26,"origin":"Leesburg, VA"},"ZaLezanic":{"player_code_id":{"code":"ZaLezanic","id":"Lezanic, Zach"},"number":"10","pos":"G","height":"6-0","height_in":72,"year_class":"Sr.","gp":5,"origin":"Berwyn, PA"},"JtDougherty":{"player_code_id":{"code":"JtDougherty","id":"Dougherty, JT"},"number":"33","pos":"F","height":"6-9","height_in":81,"year_class":"Jr.","gp":0,"origin":"River Falls, WI"},"BlBarker":{"player_code_id":{"code":"BlBarker","id":"Barker, Blake"},"number":"31","pos":"G","height":"6-2","height_in":74,"year_class":"Jr.","gp":25,"origin":"Columbus, IN"},"GrLamb":{"player_code_id":{"code":"GrLamb","id":"Lamb, Griff"},"number":"5","pos":"F","height":"6-8","height_in":80,"year_class":"Jr.","gp":1,"origin":"Holbrook, AZ"},"TaLaczkowski":{"player_code_id":{"code":"TaLaczkowski","id":"Laczkowski, Tate"},"number":"32","pos":"F","height":"6-8","height_in":80,"year_class":"Fr.","gp":3,"origin":"Dallas, TX"},"AbJohnson":{"player_code_id":{"code":"AbJohnson","id":"Johnson, Abe"},"number":"54","pos":"F","height":"6-8","height_in":80,"year_class":"Sr.","gp":31,"origin":"Missoula, MT"},"JoScovens":{"player_code_id":{"code":"JoScovens","id":"Scovens, Josh"},"number":"4","pos":"F","height":"6-4","height_in":76,"year_class":"Fr.","gp":32,"origin":"Greensboro, NC"},"TjSmall":{"player_code_id":{"code":"TjSmall","id":"Small, TJ"},"number":"35","pos":"G","height":"6-2","height_in":74,"year_class":"Jr.","gp":30,"origin":"Kenner, LA"},"__coach__":{"player_code_id":{"code":"__coach__","id":"Kevin Kuwik"},"number":"","pos":"","height":"","year_class":"","gp":-1},"JaMayo":{"player_code_id":{"code":"JaMayo","id":"Mayo, Jackson"},"number":"21","pos":"G","height":"6-0","height_in":72,"year_class":"So.","gp":3,"origin":"Mililani, HI"},"ChPeterson":{"player_code_id":{"code":"ChPeterson","id":"Peterson, Charlie"},"number":"34","pos":"F","height":"6-9","height_in":81,"year_class":"Sr.","gp":32,"origin":"Indianapolis, IN"},"BlStClair":{"player_code_id":{"code":"BlStClair","id":"St. Clair, Blane"},"number":"12","pos":"G","height":"6-5","height_in":77,"year_class":"Jr.","gp":3,"origin":"Boone, NC"},"KwDavis":{"player_code_id":{"code":"KwDavis","id":"Davis, Kwabena"},"number":"22","pos":"G","height":"6-3","height_in":75,"year_class":"Sr.","gp":22,"origin":"San Antonio, TX"},"AjAllenspach":{"player_code_id":{"code":"AjAllenspach","id":"Allenspach, AJ"},"number":"55","pos":"F","height":"6-8","height_in":80,"year_class":"Jr.","gp":31,"origin":"Simpsonville, SC"},"ChPerkins":{"player_code_id":{"code":"ChPerkins","id":"Perkins, Chanse"},"number":"25","pos":"F","height":"6-4","height_in":76,"year_class":"So.","gp":2,"origin":"Houston, TX"},"KeHailey":{"player_code_id":{"code":"KeHailey","id":"Hailey, Kendall"},"number":"13","pos":"G","height":"6-3","height_in":75,"year_class":"Fr.","gp":19,"origin":"Los Angeles, CA"},"DyBlair":{"player_code_id":{"code":"DyBlair","id":"Blair, Dylan"},"number":"23","pos":"G","height":"5-9","height_in":69,"year_class":"Fr.","gp":29,"origin":"Downington, PA"},"NoNaess":{"player_code_id":{"code":"NoNaess","id":"Naess, Nolan"},"number":"41","pos":"F","height":"6-8","height_in":80,"year_class":"Jr.","gp":1,"origin":"Laguna Beach, CA"},"RyCurry":{"player_code_id":{"code":"RyCurry","id":"Curry, Ryan"},"number":"2","pos":"G","height":"6-0","height_in":72,"year_class":"Fr.","gp":32,"origin":"Montgomery, NJ"},"ZaRocco":{"player_code_id":{"code":"ZaRocco","id":"Rocco, Zach"},"number":"14","pos":"G","height":"6-1","height_in":73,"year_class":"Sr.","gp":7,"origin":"Export, PA"},"IsCaldwell":{"player_code_id":{"code":"IsCaldwell","id":"Caldwell, Isaiah"},"number":"0","pos":"G","height":"6-4","height_in":76,"year_class":"Jr.","gp":22,"origin":"Columbia, SC"},"LuBenson":{"player_code_id":{"code":"LuBenson","id":"Benson, Luke"},"number":"42","pos":"G","height":"5-11","height_in":71,"year_class":"Jr.","gp":2,"origin":"Atlanta, GA"},"MaDove":{"player_code_id":{"code":"MaDove","id":"Dove, Matt"},"number":"44","pos":"F","height":"6-10","height_in":82,"year_class":"Sr.","gp":24,"origin":"Princeton, IN"},"JoEverson":{"player_code_id":{"code":"JoEverson","id":"Everson, Jorn"},"number":"15","pos":"F","height":"6-8","height_in":80,"year_class":"So.","gp":13,"origin":"Williston, ND"}}
