{"TrPorchia":{"player_code_id":{"code":"TrPorchia","id":"Porchia, Trealyn"},"number":"21","pos":"F","height":"6-5","height_in":77,"year_class":"Fr.","gp":0,"origin":"Beaumont, TX"},"ChSmith":{"player_code_id":{"code":"ChSmith","id":"Smith IV, Charles"},"number":"4","pos":"G","height":"6-5","height_in":77,"year_class":"Sr.","gp":30,"origin":"Atlanta, GA"},"AnNunley":{"player_code_id":{"code":"AnNunley","id":"Nunley, Andre"},"number":"30","pos":"G","height":"5-10","height_in":70,"year_class":"Sr.","gp":29,"origin":"Houston, TX"},"McHarris":{"player_code_id":{"code":"McHarris","id":"Harris, Mckinley"},"number":"33","pos":"F","height":"6-5","height_in":77,"year_class":"Sr.","gp":28,"origin":"Alief, TX"},"OrHorton":{"player_code_id":{"code":"OrHorton","id":"Horton, Jr., Orlando"},"number":"12","pos":"G","height":"5-8","height_in":68,"year_class":"Fr.","gp":21,"origin":"Houston, TX"},"__coach__":{"player_code_id":{"code":"__coach__","id":"Byron Smith"},"number":"","pos":"","height":"","year_class":"","gp":-1},"JuNimmer":{"player_code_id":{"code":"JuNimmer","id":"Nimmer, Justin"},"number":"13","pos":"F","height":"6-6","height_in":78,"year_class":"Sr.","gp":17,"origin":"Desoto, TX"},"ChLane":{"player_code_id":{"code":"ChLane","id":"Lane, Jr., Charles"},"number":"1","pos":"G","height":"6-5","height_in":77,"year_class":"Sr.","gp":31,"origin":"Eatonville, FL"},"BrMyles":{"player_code_id":{"code":"BrMyles","id":"Myles, Brian"},"number":"3","pos":"F","height":"6-7","height_in":79,"year_class":"Jr.","gp":30,"origin":"Shreveport, LA"},"NiGazelas":{"player_code_id":{"code":"NiGazelas","id":"Gazelas, Nick"},"number":"11","pos":"G","height":"6-4","height_in":76,"year_class":"Sr.","gp":28,"origin":"Humble, TX"},"ChFelix":{"player_code_id":{"code":"ChFelix","id":"Felix, Jr., Chris"},"number":"25","pos":"F","height":"6-5","height_in":77,"year_class":"So.","gp":28,"origin":"Houston, TX"},"RoGiles":{"player_code_id":{"code":"RoGiles","id":"Giles, Jr., Ronell"},"number":"5","pos":"G","height":"6-4","height_in":76,"year_class":"Sr.","gp":3,"origin":"Brandywine, MD"},"KeMcgaskey":{"player_code_id":{"code":"KeMcgaskey","id":"McGaskey, Kevin"},"number":"00","pos":"G","height":"6-0","height_in":72,"year_class":"Sr.","gp":24,"origin":"Missouri City, TX"},"SyGrisby":{"player_code_id":{"code":"SyGrisby","id":"Grisby, Syrus"},"number":"15","pos":"F","height":"6-8","height_in":80,"year_class":"Sr.","gp":7,"origin":"Oklahoma City, OK"},"JaHopkins":{"player_code_id":{"code":"JaHopkins","id":"Hopkins, Javontae"},"number":"14","pos":"G","height":"6-0","height_in":72,"year_class":"Sr.","gp":28,"origin":"Houston, TX"},"JoNash":{"player_code_id":{"code":"JoNash","id":"Nash, Jonathan"},"number":"10","pos":"G","height":"6-2","height_in":74,"year_class":"Jr.","gp":1,"origin":"Katy, TX"},"MaMcreed":{"player_code_id":{"code":"MaMcreed","id":"McReed, Malachi"},"number":"22","pos":"F","height":"6-6","height_in":78,"year_class":"Jr.","gp":0,"origin":"Orlando, FL"}}
