{"PeFrey":{"player_code_id":{"code":"PeFrey","id":"Frey, Peyton"},"number":"12","pos":"G","height":"6-6","height_in":78,"year_class":"Fr","gp":0},"SaPhilip":{"player_code_id":{"code":"SaPhilip","id":"Philip, Sabry"},"number":"1","pos":"G","height":"6-4","height_in":76,"year_class":"Sr","gp":0},"ToOnyekonwu":{"player_code_id":{"code":"ToOnyekonwu","id":"Onyekonwu, Toby"},"number":"3","pos":"G","height":"6-0","height_in":72,"year_class":"So","gp":0},"KeFitzmorris":{"player_code_id":{"code":"KeFitzmorris","id":"Fitzmorris, Keenan"},"number":"32","pos":"C","height":"7-0","height_in":84,"year_class":"Sr","gp":0},"RaFrederick":{"player_code_id":{"code":"RaFrederick","id":"Frederick, Ra'Sean"},"number":"11","pos":"G","height":"6-5","height_in":77,"year_class":"So","gp":0},"RoMuratori":{"player_code_id":{"code":"RoMuratori","id":"Muratori, Rocco"},"number":"34","pos":"C","height":"7-3","height_in":87,"year_class":"So","gp":0},"ChMaidoh":{"player_code_id":{"code":"ChMaidoh","id":"Maidoh, Chris"},"number":"4","pos":"F","height":"6-10","height_in":82,"year_class":"Sr","gp":0},"TyStephenson":{"player_code_id":{"code":"TyStephenson","id":"Stephenson-Moore, Tyler"},"number":"14","pos":"G","height":"6-3","height_in":75,"year_class":"Sr","gp":0},"JaFrey":{"player_code_id":{"code":"JaFrey","id":"Frey, Jared"},"number":"24","pos":"G","height":"6-4","height_in":76,"year_class":"So","gp":0},"KaSpace":{"player_code_id":{"code":"KaSpace","id":"Space, Kaiden"},"number":"23","pos":"G","height":"6-0","height_in":72,"year_class":"Fr","gp":0},"AnSnoddy":{"player_code_id":{"code":"AnSnoddy","id":"Snoddy, Andre"},"number":"21","pos":"G","height":"6-6","height_in":78,"year_class":"So","gp":0},"LeNahar":{"player_code_id":{"code":"LeNahar","id":"Nahar, Leon"},"number":"33","pos":"F","height":"6-10","height_in":82,"year_class":"So","gp":0},"AaClarke":{"player_code_id":{"code":"AaClarke","id":"Clarke, Aaron"},"number":"5","pos":"G","height":"6-1","height_in":73,"year_class":"Sr","gp":0},"DeNoll":{"player_code_id":{"code":"DeNoll","id":"Noll, Dean"},"number":"13","pos":"G","height":"6-2","height_in":74,"year_class":"Sr","gp":0}}
