{"TyHendricks":{"player_code_id":{"code":"TyHendricks","id":"Hendricks, Tyler"},"number":"15","pos":"G","height":"6-6","height_in":78,"year_class":"Fr","gp":0},"NiMachowski":{"player_code_id":{"code":"NiMachowski","id":"Machowski, Nils"},"number":"22","pos":"G","height":"6-3","height_in":75,"year_class":"Fr","gp":0},"PoWarakulnuk":{"player_code_id":{"code":"PoWarakulnuk","id":"Warakulnukroh, Poohpha"},"number":"20","pos":"G","height":"5-11","height_in":71,"year_class":"So","gp":0},"MaAvery":{"player_code_id":{"code":"MaAvery","id":"Avery, Marchelus"},"number":"13","pos":"F","height":"6-7","height_in":79,"year_class":"Sr","gp":0},"CjWalker":{"player_code_id":{"code":"CjWalker","id":"Walker, C.J."},"number":"21","pos":"F","height":"6-8","height_in":80,"year_class":"Sr","gp":0},"CoEmuobor":{"player_code_id":{"code":"CoEmuobor","id":"Emuobor, Comeh"},"number":"4","pos":"G","height":"6-5","height_in":77,"year_class":"Fr","gp":0},"ChMay":{"player_code_id":{"code":"ChMay","id":"May, Charlie"},"number":"0","pos":"G","height":"6-5","height_in":77,"year_class":"Fr","gp":0},"MiMockus":{"player_code_id":{"code":"MiMockus","id":"Mockus, Mintautas"},"number":"10","pos":"G","height":"6-7","height_in":79,"year_class":"Fr","gp":0},"ThSylla":{"player_code_id":{"code":"ThSylla","id":"Sylla, Thierno"},"number":"31","pos":"F","height":"6-11","height_in":83,"year_class":"So","gp":0},"ShAllen":{"player_code_id":{"code":"ShAllen","id":"Allen, Shemarri"},"number":"2","pos":"G","height":"6-4","height_in":76,"year_class":"Sr","gp":0},"JaSellers":{"player_code_id":{"code":"JaSellers","id":"Sellers, Jaylin"},"number":"24","pos":"G","height":"6-4","height_in":76,"year_class":"Jr","gp":0},"DeLangford":{"player_code_id":{"code":"DeLangford","id":"Langford Jr., DeMarr"},"number":"12","pos":"G","height":"6-5","height_in":77,"year_class":"Sr","gp":0},"DaJohnson":{"player_code_id":{"code":"DaJohnson","id":"Johnson, Darius"},"number":"3","pos":"G","height":"6-1","height_in":73,"year_class":"Jr","gp":0},"OmPayne":{"player_code_id":{"code":"OmPayne","id":"Payne, Omar"},"number":"5","pos":"F","height":"6-10","height_in":82,"year_class":"Sr","gp":0},"IbDiallo":{"player_code_id":{"code":"IbDiallo","id":"Diallo, Ibrahima"},"number":"11","pos":"F","height":"7-0","height_in":84,"year_class":"Sr","gp":0},"MiKalina":{"player_code_id":{"code":"MiKalina","id":"Kalina, Michael"},"number":"14","pos":"G","height":"6-1","height_in":73,"year_class":"Fr","gp":0},"AnJones":{"player_code_id":{"code":"AnJones","id":"Jones, Antwann"},"number":"1","pos":"G","height":"6-6","height_in":78,"year_class":"Sr","gp":0}}
